color_analysis_tool/__init__.py
color_analysis_tool/analyzer.py
color_analysis_tool/cli.py
color_analysis_tool-1.0.2.dist-info/METADATA
color_analysis_tool-1.0.2.dist-info/WHEEL
color_analysis_tool-1.0.2.dist-info/entry_points.txt
color_analysis_tool-1.0.2.dist-info/licenses/LICENSE
color_analysis_tool-1.0.2.dist-info/RECORD
