Metadata-Version: 2.4
Name: color-analysis-tool
Version: 1.0.2
Summary: A comprehensive tool for analyzing colors in images with harmony calculations and multiple color space conversions
Project-URL: Homepage, https://github.com/MichailSemoglou/color-analysis-tool
Project-URL: Repository, https://github.com/MichailSemoglou/color-analysis-tool
Project-URL: Documentation, https://github.com/MichailSemoglou/color-analysis-tool#readme
Project-URL: Issues, https://github.com/MichailSemoglou/color-analysis-tool/issues
Project-URL: Changelog, https://github.com/MichailSemoglou/color-analysis-tool/blob/main/CHANGELOG.md
Author: Michail Semoglou
Maintainer: Michail Semoglou
License-Expression: MIT
License-File: LICENSE
Keywords: CMYK,HEX,RGB,batch processing,color,color analysis,color extraction,color harmony,color space,design tools,dominant color,image processing
Classifier: Development Status :: 5 - Production/Stable
Classifier: Environment :: Console
Classifier: Intended Audience :: Developers
Classifier: Intended Audience :: End Users/Desktop
Classifier: Intended Audience :: Science/Research
Classifier: License :: OSI Approved :: MIT License
Classifier: Operating System :: OS Independent
Classifier: Programming Language :: Python :: 3
Classifier: Programming Language :: Python :: 3.7
Classifier: Programming Language :: Python :: 3.8
Classifier: Programming Language :: Python :: 3.9
Classifier: Programming Language :: Python :: 3.10
Classifier: Programming Language :: Python :: 3.11
Classifier: Programming Language :: Python :: 3.12
Classifier: Topic :: Artistic Software
Classifier: Topic :: Multimedia :: Graphics
Classifier: Topic :: Multimedia :: Graphics :: Graphics Conversion
Classifier: Topic :: Scientific/Engineering :: Image Processing
Classifier: Topic :: Scientific/Engineering :: Visualization
Classifier: Typing :: Typed
Requires-Python: >=3.7
Requires-Dist: pillow>=9.0.0
Requires-Dist: tqdm>=4.65.0
Provides-Extra: dev
Requires-Dist: black>=23.0.0; extra == 'dev'
Requires-Dist: build>=0.10.0; extra == 'dev'
Requires-Dist: flake8>=6.0.0; extra == 'dev'
Requires-Dist: isort>=5.12.0; extra == 'dev'
Requires-Dist: mypy>=1.0.0; extra == 'dev'
Requires-Dist: pytest-cov>=4.0.0; extra == 'dev'
Requires-Dist: pytest>=7.0.0; extra == 'dev'
Requires-Dist: twine>=4.0.0; extra == 'dev'
